README.rst
setup.py
docutils_ast_writer.egg-info/PKG-INFO
docutils_ast_writer.egg-info/SOURCES.txt
docutils_ast_writer.egg-info/dependency_links.txt
docutils_ast_writer.egg-info/entry_points.txt
docutils_ast_writer.egg-info/requires.txt
docutils_ast_writer.egg-info/top_level.txt
rst2ast/__init__.py
rst2ast/cmd.py
rst2ast/writer.py