Metadata-Version: 1.0
Name: docutils-ast-writer
Version: 0.1.2
Summary: AST Writer for docutils
Home-page: https://github.com/jimo1001/docutils-ast-writer
Author: jimo1001
Author-email: jimo1001@gmail.com
License: MIT
Platform: UNKNOWN
